README.md
setup.cfg
setup.py
py_solana_cli/__init__.py
py_solana_cli/account.py
py_solana_cli/client.py
py_solana_cli/contract.py
py_solana_cli.egg-info/PKG-INFO
py_solana_cli.egg-info/SOURCES.txt
py_solana_cli.egg-info/dependency_links.txt
py_solana_cli.egg-info/not-zip-safe
py_solana_cli.egg-info/requires.txt
py_solana_cli.egg-info/top_level.txt