Metadata-Version: 2.1
Name: py_solana_cli
Version: 1.4
Summary: SolanaCLI on Python
Author-email: hzhz191119111911@gmail.com
Classifier: Programming Language :: Python :: 3
Classifier: License :: OSI Approved :: MIT License
Classifier: Operating System :: OS Independent
Requires-Dist: requests
